{
    "bent_general": "0",
    "bext_general": "0",
    "date_yyyymmdd": "20160810",
    "end_time": "2017-11-18T09:46:55",
    "householdid": "THL1037",
    "householdid_key": "THL1037_20160810",
    "meta_devid": "865770021186293",
    "onfarm_country": "T",
    "onfarm_enum": "77",
    "onfarm_subnatarea": "HL",
    "onfarm_village": "77",
    "originid": "FORMHUB-JSON",
    "phone_number": "",
    "rowuuid": "31458533-2ed0-4fb0-b45b-216ac0a555f1",
    "start_time": "2017-11-18T09:46:30",
    "subscriber_id": "640092916627260",
    "survey_date": "2016-08-10T00:00:00",
    "surveyid": "1215a2d4-a4eb-402a-afd0-8a45e0a02e6b"
}
