{
    "bent_general": "0",
    "bext_general": "0",
    "date_yyyymmdd": "20171126",
    "end_time": "2017-11-26T01:09:21",
    "householdid": "ETG2268",
    "householdid_key": "ETG2268_20171126",
    "meta_devid": "865770021186111",
    "onfarm_country": "E",
    "onfarm_enum": "180",
    "onfarm_subnatarea": "TG",
    "onfarm_village": "180",
    "originid": "FORMHUB-JSON",
    "phone_number": "",
    "rowuuid": "5b9ee0ab-dbc6-49d0-b40e-2ea02e6a1b5a",
    "start_time": "2017-11-26T00:50:46",
    "subscriber_id": "636013074879882",
    "survey_date": "2017-11-26T00:00:00",
    "surveyid": "2afcf5aa-3490-4bfc-8a42-b910fc2839e1"
}
