{
    "bent_general": "0",
    "bext_general": "0",
    "date_yyyymmdd": "20170730",
    "end_time": "2017-07-30T22:19:08",
    "householdid": "THL1112",
    "householdid_key": "THL1112_20170730",
    "meta_devid": "865770021190295",
    "onfarm_country": "T",
    "onfarm_enum": "79",
    "onfarm_subnatarea": "HL",
    "onfarm_village": "79",
    "originid": "FORMHUB-JSON",
    "phone_number": "",
    "rowuuid": "0955da21-dad3-4db2-90ac-ae5e6446a03c",
    "start_time": "2017-07-30T22:18:41",
    "subscriber_id": "640092914893918",
    "survey_date": "2017-07-30T00:00:00",
    "surveyid": "30d66f7a-1595-4676-b703-1f347cabfde4"
}
