{
    "bent_general": "0",
    "bext_general": "1",
    "birdentext_rpt_birdexit": [
        {
            "bexit_comments": "",
            "bext_birdexitedcountacgg": "13",
            "bext_birdexitedcounthhnontag": "0",
            "bext_birdexitedcounthhtag": "0",
            "bext_birdtype": "0",
            "bext_birdtypeacgg": "1",
            "bext_birdtypehhnontag": "0",
            "bext_birdtypehhtag": "0",
            "birdentext_rpt_birdexitedacgg": [
                {
                    "bexit_birdexitedacggcomments": "",
                    "bexit_birdexitedacggmoney": "0",
                    "bexit_birdexitedacggposition": "2",
                    "bexit_birdexitedacggsymptoms": "7",
                    "bexit_birdexitedacggtag": "X0318",
                    "bext_birdexitedacggreason": "1",
                    "birdentext_rpt_birdexitedacgg_msel_bexit_birdexitedacggsymptoms": [
                        {
                            "bexit_birdexitedacggsymptoms": "7",
                            "householdid_key": "NNS1401_20161112",
                            "rowuuid": "3c401365-fba7-4fa2-8a2e-31cc48b88fea",
                            "rpt_birdexit_rowid": "1",
                            "rpt_birdexitedacgg_rowid": "2"
                        }
                    ],
                    "householdid_key": "NNS1401_20161112",
                    "rowuuid": "86cf87e6-1a05-4c20-b01d-6bc4dd1b74da",
                    "rpt_birdexit_rowid": "1",
                    "rpt_birdexitedacgg_rowid": "2"
                },
                {
                    "bexit_birdexitedacggcomments": "",
                    "bexit_birdexitedacggmoney": "0",
                    "bexit_birdexitedacggposition": "3",
                    "bexit_birdexitedacggsymptoms": "7",
                    "bexit_birdexitedacggtag": "X0393",
                    "bext_birdexitedacggreason": "1",
                    "birdentext_rpt_birdexitedacgg_msel_bexit_birdexitedacggsymptoms": [
                        {
                            "bexit_birdexitedacggsymptoms": "7",
                            "householdid_key": "NNS1401_20161112",
                            "rowuuid": "5ab95803-074a-4940-a936-79fde6a5d2bb",
                            "rpt_birdexit_rowid": "1",
                            "rpt_birdexitedacgg_rowid": "3"
                        }
                    ],
                    "householdid_key": "NNS1401_20161112",
                    "rowuuid": "400c5e46-7939-475d-b5d4-81a8f4e44238",
                    "rpt_birdexit_rowid": "1",
                    "rpt_birdexitedacgg_rowid": "3"
                },
                {
                    "bexit_birdexitedacggcomments": "",
                    "bexit_birdexitedacggmoney": "0",
                    "bexit_birdexitedacggposition": "4",
                    "bexit_birdexitedacggsymptoms": "7",
                    "bexit_birdexitedacggtag": "X0343",
                    "bext_birdexitedacggreason": "1",
                    "birdentext_rpt_birdexitedacgg_msel_bexit_birdexitedacggsymptoms": [
                        {
                            "bexit_birdexitedacggsymptoms": "7",
                            "householdid_key": "NNS1401_20161112",
                            "rowuuid": "20aad483-56ac-4a04-9544-9df4a5ce1c18",
                            "rpt_birdexit_rowid": "1",
                            "rpt_birdexitedacgg_rowid": "4"
                        }
                    ],
                    "householdid_key": "NNS1401_20161112",
                    "rowuuid": "e6f65d29-2f93-4a97-9488-eff9339d720f",
                    "rpt_birdexit_rowid": "1",
                    "rpt_birdexitedacgg_rowid": "4"
                },
                {
                    "bexit_birdexitedacggcomments": "",
                    "bexit_birdexitedacggmoney": "0",
                    "bexit_birdexitedacggposition": "5",
                    "bexit_birdexitedacggsymptoms": "7",
                    "bexit_birdexitedacggtag": "X0314",
                    "bext_birdexitedacggreason": "1",
                    "birdentext_rpt_birdexitedacgg_msel_bexit_birdexitedacggsymptoms": [
                        {
                            "bexit_birdexitedacggsymptoms": "7",
                            "householdid_key": "NNS1401_20161112",
                            "rowuuid": "4db3725b-1490-44a8-8b11-487323af4a5f",
                            "rpt_birdexit_rowid": "1",
                            "rpt_birdexitedacgg_rowid": "5"
                        }
                    ],
                    "householdid_key": "NNS1401_20161112",
                    "rowuuid": "4e6157c7-2835-47dd-b37d-c153701f9a5f",
                    "rpt_birdexit_rowid": "1",
                    "rpt_birdexitedacgg_rowid": "5"
                },
                {
                    "bexit_birdexitedacggcomments": "",
                    "bexit_birdexitedacggmoney": "0",
                    "bexit_birdexitedacggposition": "6",
                    "bexit_birdexitedacggsymptoms": "7",
                    "bexit_birdexitedacggtag": "X0307",
                    "bext_birdexitedacggreason": "1",
                    "birdentext_rpt_birdexitedacgg_msel_bexit_birdexitedacggsymptoms": [
                        {
                            "bexit_birdexitedacggsymptoms": "7",
                            "householdid_key": "NNS1401_20161112",
                            "rowuuid": "a3c5dfe8-1285-4dbe-8429-a4514db66bfd",
                            "rpt_birdexit_rowid": "1",
                            "rpt_birdexitedacgg_rowid": "6"
                        }
                    ],
                    "householdid_key": "NNS1401_20161112",
                    "rowuuid": "59a69637-ef7f-4d81-990d-2e443f887ec6",
                    "rpt_birdexit_rowid": "1",
                    "rpt_birdexitedacgg_rowid": "6"
                },
                {
                    "bexit_birdexitedacggcomments": "",
                    "bexit_birdexitedacggmoney": "0",
                    "bexit_birdexitedacggposition": "7",
                    "bexit_birdexitedacggsymptoms": "7",
                    "bexit_birdexitedacggtag": "X0338",
                    "bext_birdexitedacggreason": "1",
                    "birdentext_rpt_birdexitedacgg_msel_bexit_birdexitedacggsymptoms": [
                        {
                            "bexit_birdexitedacggsymptoms": "7",
                            "householdid_key": "NNS1401_20161112",
                            "rowuuid": "fa7d7fa9-3a90-4409-9266-cbcf77138c6b",
                            "rpt_birdexit_rowid": "1",
                            "rpt_birdexitedacgg_rowid": "7"
                        }
                    ],
                    "householdid_key": "NNS1401_20161112",
                    "rowuuid": "30d028cb-7b97-4ebe-ae94-577cf0e1ba8a",
                    "rpt_birdexit_rowid": "1",
                    "rpt_birdexitedacgg_rowid": "7"
                },
                {
                    "bexit_birdexitedacggcomments": "",
                    "bexit_birdexitedacggmoney": "0",
                    "bexit_birdexitedacggposition": "8",
                    "bexit_birdexitedacggsymptoms": "7",
                    "bexit_birdexitedacggtag": "X0363",
                    "bext_birdexitedacggreason": "1",
                    "birdentext_rpt_birdexitedacgg_msel_bexit_birdexitedacggsymptoms": [
                        {
                            "bexit_birdexitedacggsymptoms": "7",
                            "householdid_key": "NNS1401_20161112",
                            "rowuuid": "40d2bf33-07f1-43c6-b88f-101bf2a55416",
                            "rpt_birdexit_rowid": "1",
                            "rpt_birdexitedacgg_rowid": "8"
                        }
                    ],
                    "householdid_key": "NNS1401_20161112",
                    "rowuuid": "acd4d3dd-fe02-45e8-86ae-06ea40a064fb",
                    "rpt_birdexit_rowid": "1",
                    "rpt_birdexitedacgg_rowid": "8"
                },
                {
                    "bexit_birdexitedacggcomments": "",
                    "bexit_birdexitedacggmoney": "0",
                    "bexit_birdexitedacggposition": "9",
                    "bexit_birdexitedacggsymptoms": "7",
                    "bexit_birdexitedacggtag": "X0316",
                    "bext_birdexitedacggreason": "1",
                    "birdentext_rpt_birdexitedacgg_msel_bexit_birdexitedacggsymptoms": [
                        {
                            "bexit_birdexitedacggsymptoms": "7",
                            "householdid_key": "NNS1401_20161112",
                            "rowuuid": "728bb2f6-9a5d-444f-b4b7-9719b9f4192b",
                            "rpt_birdexit_rowid": "1",
                            "rpt_birdexitedacgg_rowid": "9"
                        }
                    ],
                    "householdid_key": "NNS1401_20161112",
                    "rowuuid": "0fed0c42-13d7-464f-a7ad-f5f78aec45c6",
                    "rpt_birdexit_rowid": "1",
                    "rpt_birdexitedacgg_rowid": "9"
                },
                {
                    "bexit_birdexitedacggcomments": "",
                    "bexit_birdexitedacggmoney": "0",
                    "bexit_birdexitedacggposition": "10",
                    "bexit_birdexitedacggsymptoms": "7",
                    "bexit_birdexitedacggtag": "X0364",
                    "bext_birdexitedacggreason": "1",
                    "birdentext_rpt_birdexitedacgg_msel_bexit_birdexitedacggsymptoms": [
                        {
                            "bexit_birdexitedacggsymptoms": "7",
                            "householdid_key": "NNS1401_20161112",
                            "rowuuid": "74a8b179-08bf-4765-baea-6c4a9ed4e68a",
                            "rpt_birdexit_rowid": "1",
                            "rpt_birdexitedacgg_rowid": "10"
                        }
                    ],
                    "householdid_key": "NNS1401_20161112",
                    "rowuuid": "a73a2829-292f-4c96-a207-f939fe66757f",
                    "rpt_birdexit_rowid": "1",
                    "rpt_birdexitedacgg_rowid": "10"
                },
                {
                    "bexit_birdexitedacggcomments": "",
                    "bexit_birdexitedacggmoney": "0",
                    "bexit_birdexitedacggposition": "11",
                    "bexit_birdexitedacggsymptoms": "7",
                    "bexit_birdexitedacggtag": "X0399",
                    "bext_birdexitedacggreason": "1",
                    "birdentext_rpt_birdexitedacgg_msel_bexit_birdexitedacggsymptoms": [
                        {
                            "bexit_birdexitedacggsymptoms": "7",
                            "householdid_key": "NNS1401_20161112",
                            "rowuuid": "13ad7e35-6b61-4a81-9555-5f1fbb5714bb",
                            "rpt_birdexit_rowid": "1",
                            "rpt_birdexitedacgg_rowid": "11"
                        }
                    ],
                    "householdid_key": "NNS1401_20161112",
                    "rowuuid": "cf181792-cdbd-438f-9439-f39c8228c701",
                    "rpt_birdexit_rowid": "1",
                    "rpt_birdexitedacgg_rowid": "11"
                },
                {
                    "bexit_birdexitedacggcomments": "",
                    "bexit_birdexitedacggmoney": "0",
                    "bexit_birdexitedacggposition": "12",
                    "bexit_birdexitedacggsymptoms": "7",
                    "bexit_birdexitedacggtag": "X0321",
                    "bext_birdexitedacggreason": "1",
                    "birdentext_rpt_birdexitedacgg_msel_bexit_birdexitedacggsymptoms": [
                        {
                            "bexit_birdexitedacggsymptoms": "7",
                            "householdid_key": "NNS1401_20161112",
                            "rowuuid": "1bfde570-2ebf-4322-b862-e4d5bf2ae11d",
                            "rpt_birdexit_rowid": "1",
                            "rpt_birdexitedacgg_rowid": "12"
                        }
                    ],
                    "householdid_key": "NNS1401_20161112",
                    "rowuuid": "65996fcd-9973-45a4-b498-c4df70e1a100",
                    "rpt_birdexit_rowid": "1",
                    "rpt_birdexitedacgg_rowid": "12"
                },
                {
                    "bexit_birdexitedacggcomments": "",
                    "bexit_birdexitedacggmoney": "0",
                    "bexit_birdexitedacggposition": "13",
                    "bexit_birdexitedacggsymptoms": "7",
                    "bexit_birdexitedacggtag": "X0324",
                    "bext_birdexitedacggreason": "1",
                    "birdentext_rpt_birdexitedacgg_msel_bexit_birdexitedacggsymptoms": [
                        {
                            "bexit_birdexitedacggsymptoms": "7",
                            "householdid_key": "NNS1401_20161112",
                            "rowuuid": "5aee73ea-9824-4376-849b-e0f359410dae",
                            "rpt_birdexit_rowid": "1",
                            "rpt_birdexitedacgg_rowid": "13"
                        }
                    ],
                    "householdid_key": "NNS1401_20161112",
                    "rowuuid": "1f7be556-1ec8-401c-bc64-5eb37118d02a",
                    "rpt_birdexit_rowid": "1",
                    "rpt_birdexitedacgg_rowid": "13"
                },
                {
                    "bexit_birdexitedacggcomments": "",
                    "bexit_birdexitedacggmoney": "0",
                    "bexit_birdexitedacggposition": "1",
                    "bexit_birdexitedacggsymptoms": "7",
                    "bexit_birdexitedacggtag": "X0313",
                    "bext_birdexitedacggreason": "1",
                    "birdentext_rpt_birdexitedacgg_msel_bexit_birdexitedacggsymptoms": [
                        {
                            "bexit_birdexitedacggsymptoms": "7",
                            "householdid_key": "NNS1401_20161112",
                            "rowuuid": "21ba5b75-0f66-4088-a203-f53d92e320f6",
                            "rpt_birdexit_rowid": "1",
                            "rpt_birdexitedacgg_rowid": "1"
                        }
                    ],
                    "householdid_key": "NNS1401_20161112",
                    "rowuuid": "2038065b-8f18-4871-9f21-049b1c3be410",
                    "rpt_birdexit_rowid": "1",
                    "rpt_birdexitedacgg_rowid": "1"
                }
            ],
            "householdid_key": "NNS1401_20161112",
            "rowuuid": "cd834fd0-98dc-40d5-9b91-6639fd7d2dd1",
            "rpt_birdexit_rowid": "1"
        }
    ],
    "date_yyyymmdd": "20161112",
    "end_time": "2016-11-12T14:14:43",
    "householdid": "NNS1401",
    "householdid_key": "NNS1401_20161112",
    "meta_devid": "865770021186426",
    "onfarm_country": "N",
    "onfarm_enum": "48",
    "onfarm_subnatarea": "NS",
    "onfarm_village": "48",
    "originid": "FORMHUB-JSON",
    "phone_number": "",
    "rowuuid": "a51701e3-195d-42aa-8492-ee3debb69e8e",
    "start_time": "2016-11-12T14:09:12",
    "subscriber_id": "",
    "survey_date": "2016-11-12T00:00:00",
    "surveyid": "4e6c090b-f38e-4d24-be27-33433354b789"
}
