{
    "bent_general": "0",
    "bext_general": "0",
    "date_yyyymmdd": "20170412",
    "end_time": "2017-04-19T10:38:42",
    "householdid": "ETG2309",
    "householdid_key": "ETG2309_20170412",
    "meta_devid": "865770021186376",
    "onfarm_country": "E",
    "onfarm_enum": "181",
    "onfarm_subnatarea": "TG",
    "onfarm_village": "181",
    "originid": "FORMHUB-JSON",
    "phone_number": "",
    "rowuuid": "ab56766d-dabf-4934-8265-5e8838482b78",
    "start_time": "2017-04-12T14:57:38",
    "subscriber_id": "",
    "survey_date": "2017-04-12T00:00:00",
    "surveyid": "5120ac9a-b88d-4b46-bf54-6ee66ba98ab2"
}
