{
    "bent_general": "0",
    "bext_general": "0",
    "date_yyyymmdd": "20171010",
    "end_time": "2017-11-23T09:46:22",
    "householdid": "ETG2229",
    "householdid_key": "ETG2229_20171010",
    "meta_devid": "865770027212903",
    "onfarm_country": "E",
    "onfarm_enum": "179",
    "onfarm_subnatarea": "TG",
    "onfarm_village": "179",
    "originid": "FORMHUB-JSON",
    "phone_number": "986281831",
    "rowuuid": "ebd50c13-ec7f-4fca-8979-ee5cbe4ea23d",
    "start_time": "2017-11-22T11:36:51",
    "subscriber_id": "636013082319932",
    "survey_date": "2017-10-10T00:00:00",
    "surveyid": "5218bcee-7f47-45f5-8d03-d93c3ffdf52e"
}
