{
    "bent_general": "0",
    "bext_general": "0",
    "date_yyyymmdd": "20170721",
    "end_time": "2017-08-10T08:53:00",
    "householdid": "EAM2411",
    "householdid_key": "EAM2411_20170721",
    "meta_devid": "865770027208539",
    "onfarm_country": "E",
    "onfarm_enum": "169",
    "onfarm_subnatarea": "AM",
    "onfarm_village": "169",
    "originid": "FORMHUB-JSON",
    "phone_number": "975191173",
    "rowuuid": "437166cf-9c91-4c6c-93bf-e45d0ce10353",
    "start_time": "2017-07-23T10:47:41",
    "subscriber_id": "636013072020495",
    "survey_date": "2017-07-21T00:00:00",
    "surveyid": "7455b88a-f72e-43c3-b759-939cf036998c"
}
