{
    "bent_general": "0",
    "bext_general": "0",
    "date_yyyymmdd": "20170613",
    "end_time": "2017-08-16T17:57:15",
    "householdid": "EAA2131",
    "householdid_key": "EAA2131_20170613",
    "meta_devid": "865770027212762",
    "onfarm_country": "E",
    "onfarm_enum": "201",
    "onfarm_subnatarea": "AA",
    "onfarm_village": "201",
    "originid": "FORMHUB-JSON",
    "phone_number": "",
    "rowuuid": "fdbb996b-de8c-4fb6-bfd8-427c10b34f20",
    "start_time": "2017-08-16T17:56:30",
    "subscriber_id": "636013058994664",
    "survey_date": "2017-06-13T00:00:00",
    "surveyid": "7b660042-981c-45a0-9a34-093a6e690bcd"
}
