{
    "bent_general": "0",
    "bext_general": "1",
    "birdentext_rpt_birdexit": [
        {
            "bexit_comments": "week 20",
            "bext_birdexitedcountacgg": "8",
            "bext_birdexitedcounthhnontag": "0",
            "bext_birdexitedcounthhtag": "0",
            "bext_birdtype": "0",
            "bext_birdtypeacgg": "1",
            "bext_birdtypehhnontag": "0",
            "bext_birdtypehhtag": "0",
            "birdentext_rpt_birdexitedacgg": [
                {
                    "bexit_birdexitedacggcomments": "cannibalism",
                    "bexit_birdexitedacggmoney": "0",
                    "bexit_birdexitedacggposition": "2",
                    "bexit_birdexitedacggsymptoms": "",
                    "bexit_birdexitedacggtag": "Z0153",
                    "bext_birdexitedacggreason": "14",
                    "householdid_key": "EAA2033_20170124",
                    "rowuuid": "c17d1986-a7b5-4251-af7b-c87c034c867a",
                    "rpt_birdexit_rowid": "1",
                    "rpt_birdexitedacgg_rowid": "2"
                },
                {
                    "bexit_birdexitedacggcomments": "cannibalism",
                    "bexit_birdexitedacggmoney": "0",
                    "bexit_birdexitedacggposition": "3",
                    "bexit_birdexitedacggsymptoms": "",
                    "bexit_birdexitedacggtag": "Z0172",
                    "bext_birdexitedacggreason": "14",
                    "householdid_key": "EAA2033_20170124",
                    "rowuuid": "43f6f1ad-b081-4890-8ae6-627c175905b5",
                    "rpt_birdexit_rowid": "1",
                    "rpt_birdexitedacgg_rowid": "3"
                },
                {
                    "bexit_birdexitedacggcomments": "cannibalism",
                    "bexit_birdexitedacggmoney": "0",
                    "bexit_birdexitedacggposition": "4",
                    "bexit_birdexitedacggsymptoms": "",
                    "bexit_birdexitedacggtag": "Z0165",
                    "bext_birdexitedacggreason": "14",
                    "householdid_key": "EAA2033_20170124",
                    "rowuuid": "67d5bd17-e081-4269-ad1d-1f247dcccdf1",
                    "rpt_birdexit_rowid": "1",
                    "rpt_birdexitedacgg_rowid": "4"
                },
                {
                    "bexit_birdexitedacggcomments": "cannibalism",
                    "bexit_birdexitedacggmoney": "0",
                    "bexit_birdexitedacggposition": "5",
                    "bexit_birdexitedacggsymptoms": "",
                    "bexit_birdexitedacggtag": "Z0101",
                    "bext_birdexitedacggreason": "14",
                    "householdid_key": "EAA2033_20170124",
                    "rowuuid": "7f4d0f2d-02f5-4a6b-a942-05f56a1b9303",
                    "rpt_birdexit_rowid": "1",
                    "rpt_birdexitedacgg_rowid": "5"
                },
                {
                    "bexit_birdexitedacggcomments": "cannibalism",
                    "bexit_birdexitedacggmoney": "0",
                    "bexit_birdexitedacggposition": "6",
                    "bexit_birdexitedacggsymptoms": "",
                    "bexit_birdexitedacggtag": "Z0103",
                    "bext_birdexitedacggreason": "14",
                    "householdid_key": "EAA2033_20170124",
                    "rowuuid": "ad8d6e4e-d008-48b7-aa06-9d09130bd1d3",
                    "rpt_birdexit_rowid": "1",
                    "rpt_birdexitedacgg_rowid": "6"
                },
                {
                    "bexit_birdexitedacggcomments": "cannibalism",
                    "bexit_birdexitedacggmoney": "0",
                    "bexit_birdexitedacggposition": "7",
                    "bexit_birdexitedacggsymptoms": "",
                    "bexit_birdexitedacggtag": "Z0161",
                    "bext_birdexitedacggreason": "14",
                    "householdid_key": "EAA2033_20170124",
                    "rowuuid": "8e292c40-97ba-4a6c-9ed5-6c01929cb838",
                    "rpt_birdexit_rowid": "1",
                    "rpt_birdexitedacgg_rowid": "7"
                },
                {
                    "bexit_birdexitedacggcomments": "cannibalism",
                    "bexit_birdexitedacggmoney": "0",
                    "bexit_birdexitedacggposition": "8",
                    "bexit_birdexitedacggsymptoms": "",
                    "bexit_birdexitedacggtag": "Z0197",
                    "bext_birdexitedacggreason": "14",
                    "householdid_key": "EAA2033_20170124",
                    "rowuuid": "8cf759c4-71aa-4ab1-a35a-7e806536fe4d",
                    "rpt_birdexit_rowid": "1",
                    "rpt_birdexitedacgg_rowid": "8"
                },
                {
                    "bexit_birdexitedacggcomments": "cannibalism",
                    "bexit_birdexitedacggmoney": "0",
                    "bexit_birdexitedacggposition": "1",
                    "bexit_birdexitedacggsymptoms": "",
                    "bexit_birdexitedacggtag": "Z0190",
                    "bext_birdexitedacggreason": "14",
                    "householdid_key": "EAA2033_20170124",
                    "rowuuid": "4685fd46-cdae-4da4-ad3c-02e4d9fbf52c",
                    "rpt_birdexit_rowid": "1",
                    "rpt_birdexitedacgg_rowid": "1"
                }
            ],
            "householdid_key": "EAA2033_20170124",
            "rowuuid": "47f8ecdf-dbc1-45ef-ae25-2fb4ede78343",
            "rpt_birdexit_rowid": "1"
        }
    ],
    "date_yyyymmdd": "20170124",
    "end_time": "2017-01-24T04:15:19",
    "householdid": "EAA2033",
    "householdid_key": "EAA2033_20170124",
    "meta_devid": "865770027212853",
    "onfarm_country": "E",
    "onfarm_enum": "198",
    "onfarm_subnatarea": "AA",
    "onfarm_village": "198",
    "originid": "FORMHUB-JSON",
    "phone_number": "",
    "rowuuid": "2af222a8-cf2c-4cc4-9cfa-ca809b960c57",
    "start_time": "2017-01-24T04:01:34",
    "subscriber_id": "",
    "survey_date": "2017-01-24T00:00:00",
    "surveyid": "89832bd0-1d42-4980-b2af-867e0c2bc136"
}
