{
    "bent_general": "0",
    "bext_general": "0",
    "date_yyyymmdd": "20171018",
    "end_time": "2017-10-18T16:27:45",
    "householdid": "TSH1055",
    "householdid_key": "TSH1055_20171018",
    "meta_devid": "865770021184793",
    "onfarm_country": "T",
    "onfarm_enum": "62",
    "onfarm_subnatarea": "SH",
    "onfarm_village": "62",
    "originid": "FORMHUB-JSON",
    "phone_number": "",
    "rowuuid": "22fb866d-c8d4-4912-beea-5bea89443b04",
    "start_time": "2017-10-18T16:27:21",
    "subscriber_id": "640050946646607",
    "survey_date": "2017-10-18T00:00:00",
    "surveyid": "b64f7681-9f16-4d1f-a3d2-5744bb0d20f0"
}
