{
    "bent_general": "0",
    "bext_general": "0",
    "date_yyyymmdd": "20170822",
    "end_time": "2017-08-22T03:52:05",
    "householdid": "EAA2225",
    "householdid_key": "EAA2225_20170822",
    "meta_devid": "865770027212671",
    "onfarm_country": "E",
    "onfarm_enum": "203",
    "onfarm_subnatarea": "AA",
    "onfarm_village": "203",
    "originid": "FORMHUB-JSON",
    "phone_number": "",
    "rowuuid": "68e85786-f36e-4bfe-8745-75aa71af9460",
    "start_time": "2017-08-22T03:51:27",
    "subscriber_id": "",
    "survey_date": "2017-08-22T00:00:00",
    "surveyid": "c302824e-5087-403c-b631-ba32e4c9774f"
}
