{
    "bent_general": "0",
    "bext_general": "0",
    "date_yyyymmdd": "20171109",
    "end_time": "2017-11-21T11:47:36",
    "householdid": "ESR2363",
    "householdid_key": "ESR2363_20171109",
    "meta_devid": "865770021185402",
    "onfarm_country": "E",
    "onfarm_enum": "192",
    "onfarm_subnatarea": "SR",
    "onfarm_village": "192",
    "originid": "FORMHUB-JSON",
    "phone_number": "",
    "rowuuid": "be53f849-1eb4-4d70-ba4a-7ec86a4f2d71",
    "start_time": "2017-11-21T11:47:06",
    "subscriber_id": "",
    "survey_date": "2017-11-09T00:00:00",
    "surveyid": "e363a605-805c-4ea2-b048-8122559932a1"
}
