{
    "bent_general": "0",
    "bext_general": "1",
    "birdentext_rpt_birdexit": [
        {
            "bexit_comments": "Great farmer",
            "bext_birdexitedcountacgg": "1",
            "bext_birdexitedcounthhnontag": "0",
            "bext_birdexitedcounthhtag": "0",
            "bext_birdtype": "0",
            "bext_birdtypeacgg": "1",
            "bext_birdtypehhnontag": "0",
            "bext_birdtypehhtag": "0",
            "birdentext_rpt_birdexitedacgg": [
                {
                    "bexit_birdexitedacggcomments": "",
                    "bexit_birdexitedacggmoney": "0",
                    "bexit_birdexitedacggposition": "1",
                    "bexit_birdexitedacggsymptoms": "",
                    "bexit_birdexitedacggtag": "P0971",
                    "bext_birdexitedacggreason": "5",
                    "householdid_key": "NRV1028_20170220",
                    "rowuuid": "391b2994-22be-4c23-a891-ae301a7a7bca",
                    "rpt_birdexit_rowid": "1",
                    "rpt_birdexitedacgg_rowid": "1"
                }
            ],
            "householdid_key": "NRV1028_20170220",
            "rowuuid": "8cdd0e59-2b72-43ef-8d6f-cd7d4122a1fb",
            "rpt_birdexit_rowid": "1"
        }
    ],
    "date_yyyymmdd": "20170220",
    "end_time": "2017-02-20T13:55:21",
    "householdid": "NRV1028",
    "householdid_key": "NRV1028_20170220",
    "meta_devid": "865770021185576",
    "onfarm_country": "N",
    "onfarm_enum": "13",
    "onfarm_subnatarea": "RV",
    "onfarm_village": "13",
    "originid": "FORMHUB-JSON",
    "phone_number": "",
    "rowuuid": "8e09ed79-140b-462a-92a6-3420b6c56c02",
    "start_time": "2017-02-20T13:50:32",
    "subscriber_id": "621300287913841",
    "survey_date": "2017-02-20T00:00:00",
    "surveyid": "ea24bb3e-ed48-41cd-bb8d-e23a32203e81"
}
