{
    "bent_general": "0",
    "bext_general": "1",
    "birdentext_rpt_birdexit": [
        {
            "bexit_comments": "",
            "bext_birdexitedcountacgg": "3",
            "bext_birdexitedcounthhnontag": "0",
            "bext_birdexitedcounthhtag": "0",
            "bext_birdtype": "0",
            "bext_birdtypeacgg": "1",
            "bext_birdtypehhnontag": "0",
            "bext_birdtypehhtag": "0",
            "birdentext_rpt_birdexitedacgg": [
                {
                    "bexit_birdexitedacggcomments": "",
                    "bexit_birdexitedacggmoney": "0",
                    "bexit_birdexitedacggposition": "2",
                    "bexit_birdexitedacggsymptoms": "",
                    "bexit_birdexitedacggtag": "E0966",
                    "bext_birdexitedacggreason": "5",
                    "householdid_key": "NIM1034_20170301",
                    "rowuuid": "1b3ca0ee-6cc7-41eb-bc76-3fc8aefed37b",
                    "rpt_birdexit_rowid": "1",
                    "rpt_birdexitedacgg_rowid": "2"
                },
                {
                    "bexit_birdexitedacggcomments": "",
                    "bexit_birdexitedacggmoney": "0",
                    "bexit_birdexitedacggposition": "3",
                    "bexit_birdexitedacggsymptoms": "",
                    "bexit_birdexitedacggtag": "K0383",
                    "bext_birdexitedacggreason": "5",
                    "householdid_key": "NIM1034_20170301",
                    "rowuuid": "83cebb14-8eef-4e91-93b9-bd3153cb2315",
                    "rpt_birdexit_rowid": "1",
                    "rpt_birdexitedacgg_rowid": "3"
                },
                {
                    "bexit_birdexitedacggcomments": "",
                    "bexit_birdexitedacggmoney": "0",
                    "bexit_birdexitedacggposition": "1",
                    "bexit_birdexitedacggsymptoms": "",
                    "bexit_birdexitedacggtag": "N0858",
                    "bext_birdexitedacggreason": "5",
                    "householdid_key": "NIM1034_20170301",
                    "rowuuid": "00a52e70-8cdc-461d-9b94-0b48cb067ffd",
                    "rpt_birdexit_rowid": "1",
                    "rpt_birdexitedacgg_rowid": "1"
                }
            ],
            "householdid_key": "NIM1034_20170301",
            "rowuuid": "1901bba0-b8eb-4828-ac17-e1817bf24822",
            "rpt_birdexit_rowid": "1"
        }
    ],
    "date_yyyymmdd": "20170301",
    "end_time": "2017-03-01T04:45:58",
    "householdid": "NIM1034",
    "householdid_key": "NIM1034_20170301",
    "meta_devid": "865770021187093",
    "onfarm_country": "N",
    "onfarm_enum": "25",
    "onfarm_subnatarea": "IM",
    "onfarm_village": "25",
    "originid": "FORMHUB-JSON",
    "phone_number": "08155234107",
    "rowuuid": "b508fff3-5883-4978-b525-5add2a56552c",
    "start_time": "2017-03-01T04:44:03",
    "subscriber_id": "621505206759890",
    "survey_date": "2017-03-01T00:00:00",
    "surveyid": "ea6d3ad0-0411-4418-92bd-328d045d6b8c"
}
