{
    "bent_general": "0",
    "bext_general": "1",
    "birdentext_rpt_birdexit": [
        {
            "bexit_comments": "",
            "bext_birdexitedcountacgg": "2",
            "bext_birdexitedcounthhnontag": "0",
            "bext_birdexitedcounthhtag": "0",
            "bext_birdtype": "0",
            "bext_birdtypeacgg": "1",
            "bext_birdtypehhnontag": "0",
            "bext_birdtypehhtag": "0",
            "birdentext_rpt_birdexitedacgg": [
                {
                    "bexit_birdexitedacggcomments": "",
                    "bexit_birdexitedacggmoney": "200",
                    "bexit_birdexitedacggposition": "2",
                    "bexit_birdexitedacggsymptoms": "",
                    "bexit_birdexitedacggtag": "AF978",
                    "bext_birdexitedacggreason": "6",
                    "householdid_key": "ESR2153_20171016",
                    "rowuuid": "47bbe164-10ba-4ccb-8d58-5e0c39a4cb93",
                    "rpt_birdexit_rowid": "1",
                    "rpt_birdexitedacgg_rowid": "2"
                },
                {
                    "bexit_birdexitedacggcomments": "",
                    "bexit_birdexitedacggmoney": "0",
                    "bexit_birdexitedacggposition": "1",
                    "bexit_birdexitedacggsymptoms": "",
                    "bexit_birdexitedacggtag": "AF987",
                    "bext_birdexitedacggreason": "3",
                    "householdid_key": "ESR2153_20171016",
                    "rowuuid": "ff2fb5ef-46f0-48e2-bdea-63ac6488e76c",
                    "rpt_birdexit_rowid": "1",
                    "rpt_birdexitedacgg_rowid": "1"
                }
            ],
            "householdid_key": "ESR2153_20171016",
            "rowuuid": "c7fdd19d-d7d8-4267-aab7-8d6fe18897af",
            "rpt_birdexit_rowid": "1"
        }
    ],
    "date_yyyymmdd": "20171016",
    "end_time": "2017-10-16T17:53:00",
    "householdid": "ESR2153",
    "householdid_key": "ESR2153_20171016",
    "meta_devid": "865770021187358",
    "onfarm_country": "E",
    "onfarm_enum": "186",
    "onfarm_subnatarea": "SR",
    "onfarm_village": "186",
    "originid": "FORMHUB-JSON",
    "phone_number": "",
    "rowuuid": "2642a63f-df3b-45f7-8527-29a7cf7b0dd3",
    "start_time": "2017-10-16T11:33:22",
    "subscriber_id": "636013037939578",
    "survey_date": "2017-10-16T00:00:00",
    "surveyid": "f433b0a8-c110-4024-80ee-45596bb82a7f"
}
